{
  "artists": [
    {
      "id": "0",
      "name": "Lakyn",
      "username": "LakynMPhotography",
      "email": "lakynmphotography@hotmail.com",
      "password": "lakyn123",
      "artist_type": "Photographer",
      "description": "description",
      "opento_commission": "Yes"
    },
    {
      "id": "1",
      "name": "DEMS & DOLLS",
      "username": "DEMS & DOLLS",
      "email": "dems@hotmail.com",
      "password": "dems123",
      "artist_type": "Painter",
      "description": "description",
      "opento_commission": "Yes"
    },
    {
      "id": "2",
      "name": "Banksy",
      "username": "Banksy",
      "email": "banksy@gmail.com",
      "password": "banksy123",
      "artist_type": "Street artist",
      "description": "description",
      "opento_commission": "No"
    },
    {
      "id": "3",
      "name": "Waleed",
      "username": "Waleed",
      "email": "Waleed@gmail.com",
      "password": "waleed123",
      "artist_type": "Painter",
      "description": "description",
      "opento_commission": "Yes"
    },
    {
      "name": "Vincent Van Gogh",
      "username": "VinnyVG",
      "email": "vvg@gmail.com",
      "password": "vincent",
      "artist_type": "Painter",
      "opento_commission": "No",
      "description": "description",
      "id": "4"
    }
  ]
}